pycodec/__init__.py
pycodec/compress/__init__.py
pycodec/crypto/__init__.py
pycodec/crypto/cipher/__init__.py
pycodec/crypto/cipher/aes.py
pycodec/crypto/cipher/des.py
pycodec/crypto/cipher/des3.py
pycodec/crypto/valid/__init__.py
pycodec/crypto/valid/hmac.py
pycodec/hash/__init__.py
pycodec/hash/md5.py
pycodec/hash/sha1.py
pycodec/hash/sha2.py
pycodec/valid/__init__.py
pycodec/valid/crc16.py
pycodec/valid/crc32.py
pycodec/valid/crc8.py
pycodec-0.0.2.dist-info/METADATA
pycodec-0.0.2.dist-info/RECORD
pycodec-0.0.2.dist-info/WHEEL
pycodec-0.0.2.dist-info/top_level.txt
tests/__init__.py
tests/crypto/__init__.py
tests/crypto/valid/__init__.py
tests/crypto/valid/hmac_tests.py
tests/hash/__init__.py
tests/hash/sha1_tests.py
tests/hash/sha2_tests.py
