Metadata-Version: 2.1
Name: pycodec
Version: 0.0.2
Summary: PyCodec is a package for coding and decoding any message by any Coders and Decoders also as Crypto Coders and Crypto Decoders
Home-page: https://github.com/redradist/PyCodec.git
Author: Denis Kotov (redradist, RedRadist, redra, RedRa)
Author-email: redradist@gmail.com
License: UNKNOWN
Platform: UNKNOWN
Classifier: Programming Language :: Python :: 3
Classifier: License :: OSI Approved :: MIT License
Classifier: Operating System :: OS Independent
